[
  {
    "original": "MAP BY MIDRAN KIDRAN",
    "en_trans": "",
    "zh_trans": "地图由Midran Kidran制作",
    "jp_trans": "",
    "kr_trans": "",
    "timer_num": 0,
    "enable_timer": 0
  },
  {
    "original": "THANKS MAPEADORES FOR TESTING",
    "en_trans": "",
    "zh_trans": "感谢Mapeadores提供的测试",
    "jp_trans": "",
    "kr_trans": "",
    "timer_num": 0,
    "enable_timer": 0
  },
  {
    "original": ">>> DOOR BREAKS IN 20 SECONDS <<<",
    "en_trans": "",
    "zh_trans": ">>> 门在 20 秒后开启 <<<",
    "jp_trans": "",
    "kr_trans": "",
    "timer_num": 20,
    "enable_timer": 1
  },
  {
    "original": "!!! ZOMBIES TELEPORT IN 7 SECONDS !!!",
    "en_trans": "",
    "zh_trans": "!!! 僵尸 7 秒后传送 !!!",
    "jp_trans": "",
    "kr_trans": "",
    "timer_num": 7,
    "enable_timer": 1
  },
  {
    "original": ">>> SHOOT THE GATE <<<",
    "en_trans": "",
    "zh_trans": ">>> 快射大门! <<<",
    "jp_trans": "",
    "kr_trans": "",
    "timer_num": 0,
    "enable_timer": 0
  },
  {
    "original": ">>> SECOND GATE BREAKS IN 20 SECONDS <<<",
    "en_trans": "",
    "zh_trans": ">>> 第二扇大门 20 秒后开启 <<<",
    "jp_trans": "",
    "kr_trans": "",
    "timer_num": 20,
    "enable_timer": 1
  },
  {
    "original": ">>> THE GATE WILL OPEN IN 10 SECONDS <<<",
    "en_trans": "",
    "zh_trans": ">>> 大门 10 秒后开启 <<<",
    "jp_trans": "",
    "kr_trans": "",
    "timer_num": 10,
    "enable_timer": 1
  },
  {
    "original": ">>> DOOR BREAKS IN 15 SECONDS <<<",
    "en_trans": "",
    "zh_trans": ">>> 门 15 秒后开启 <<<",
    "jp_trans": "",
    "kr_trans": "",
    "timer_num": 15,
    "enable_timer": 1
  },
  {
    "original": "!!! ZOMBIES TELEPORT IN 10 SECONDS !!!",
    "en_trans": "",
    "zh_trans": "!!! 僵尸 10 秒后传送 !!!",
    "jp_trans": "",
    "kr_trans": "",
    "timer_num": 10,
    "enable_timer": 1
  },
  {
    "original": "DOOR BREAKS IN 25 SECONDS",
    "en_trans": "",
    "zh_trans": "门在 25 秒后开启",
    "jp_trans": "",
    "kr_trans": "",
    "timer_num": 25,
    "enable_timer": 1
  },
  {
    "original": "!!! ZOMBIES TP IN 10 SECONDS !!!",
    "en_trans": "",
    "zh_trans": "!!! 僵尸 10 秒后传送 !!!",
    "jp_trans": "",
    "kr_trans": "",
    "timer_num": 10,
    "enable_timer": 1
  },
  {
    "original": ">>> GATE OPENS IN 20 SECONDS <<<",
    "en_trans": "",
    "zh_trans": ">>> 大门 20 秒后开启 <<<",
    "jp_trans": "",
    "kr_trans": "",
    "timer_num": 20,
    "enable_timer": 1
  },
  {
    "original": ">>> GATE CLOSES IN 10 SECONDS <<<",
    "en_trans": "",
    "zh_trans": ">>> 大门 10 秒后关闭 <<<",
    "jp_trans": "",
    "kr_trans": "",
    "timer_num": 10,
    "enable_timer": 1
  },
  {
    "original": ">>> SURVIVE FOR 40 SECONDS <<<",
    "en_trans": "",
    "zh_trans": ">>> 生存 40 秒 <<<",
    "jp_trans": "",
    "kr_trans": "",
    "timer_num": 40,
    "enable_timer": 1
  },
  {
    "original": ">>> GATE OPENS IN 10 SECONDS <<<",
    "en_trans": "",
    "zh_trans": ">>> 大门 10 秒后开启 <<<",
    "jp_trans": "",
    "kr_trans": "",
    "timer_num": 10,
    "enable_timer": 1
  },
  {
    "original": "!!! ZOMBIES TELEPORT IN 15 SECONDS !!!",
    "en_trans": "",
    "zh_trans": "!!! 僵尸 15 秒后传送 !!!",
    "jp_trans": "",
    "kr_trans": "",
    "timer_num": 15,
    "enable_timer": 1
  },
  {
    "original": ">>> FINAL DOOR OPENS IN 30 SECONDS <<<",
    "en_trans": "",
    "zh_trans": ">>> 最后的门 30 秒后开启 <<<",
    "jp_trans": "",
    "kr_trans": "",
    "timer_num": 30,
    "enable_timer": 1
  },
  {
    "original": ">>> FINAL DOOR CLOSES IN 20 SECONDS <<<",
    "en_trans": "",
    "zh_trans": ">>> 最后的门 20 秒后开启 <<<",
    "jp_trans": "",
    "kr_trans": "",
    "timer_num": 20,
    "enable_timer": 1
  },
  {
    "original": "!!! ZOMBIES TP IN 20 SECONDS !!!",
    "en_trans": "",
    "zh_trans": "",
    "jp_trans": "",
    "kr_trans": "",
    "timer_num": 20,
    "enable_timer": 1
  },
  {
    "original": ">>> GATE STARTS OPENING IN 20 SECONDS <<<",
    "en_trans": "",
    "zh_trans": "",
    "jp_trans": "",
    "kr_trans": "",
    "timer_num": 20,
    "enable_timer": 1
  }
]