[
  {
    "original": "WARMUP ROUND - WAITING PLAYERS TO CONNECT",
    "en_trans": "",
    "zh_trans": "",
    "jp_trans": "",
    "kr_trans": "",
    "timer_num": 0,
    "enable_timer": 0
  },
  {
    "original": "**ZE_FFXII_FEYWOOD**",
    "en_trans": "",
    "zh_trans": "",
    "jp_trans": "",
    "kr_trans": "",
    "timer_num": 0,
    "enable_timer": 0
  },
  {
    "original": "**MAP BY HaRyDe & Headshooter.SC**",
    "en_trans": "",
    "zh_trans": "",
    "jp_trans": "",
    "kr_trans": "",
    "timer_num": 0,
    "enable_timer": 0
  },
  {
    "original": "**WARMUP ROUND**",
    "en_trans": "",
    "zh_trans": "",
    "jp_trans": "",
    "kr_trans": "",
    "timer_num": 0,
    "enable_timer": 0
  },
  {
    "original": "**Special thanks to Kaesar Batnik_Ref.smd Kaem Hannibal[SPA] (effects from his maps) and Slayerdragon**",
    "en_trans": "",
    "zh_trans": "",
    "jp_trans": "",
    "kr_trans": "",
    "timer_num": 0,
    "enable_timer": 0
  },
  {
    "original": "[MAP HINT MASTER] THE MAP HAS 11 SPECIAL ITEMS - 7 FOR HUMANS",
    "en_trans": "",
    "zh_trans": "",
    "jp_trans": "",
    "kr_trans": "",
    "timer_num": 11,
    "enable_timer": 1
  }
]