[
  {
    "original": "***MAP BY - LUFFAREN***",
    "en_trans": "",
    "zh_trans": "",
    "jp_trans": "",
    "kr_trans": "",
    "timer_num": 0,
    "enable_timer": 0
  },
  {
    "original": "***DO NOT TRY TO TAKE SHORTCUTS - IT WILL RESULT IN TELEPORTING BACK***",
    "en_trans": "",
    "zh_trans": "",
    "jp_trans": "",
    "kr_trans": "",
    "timer_num": 0,
    "enable_timer": 0
  },
  {
    "original": "***FOLLOW THE ARROWS TO AVOID DEAD ENDS***",
    "en_trans": "",
    "zh_trans": "",
    "jp_trans": "",
    "kr_trans": "",
    "timer_num": 0,
    "enable_timer": 0
  },
  {
    "original": "***LEVER GOING UP IN 5 SECONDS***",
    "en_trans": "",
    "zh_trans": "",
    "jp_trans": "",
    "kr_trans": "",
    "timer_num": 5,
    "enable_timer": 1
  },
  {
    "original": "***DOOR OPENING IN 10 SECONDS***",
    "en_trans": "",
    "zh_trans": "",
    "jp_trans": "",
    "kr_trans": "",
    "timer_num": 10,
    "enable_timer": 1
  },
  {
    "original": "***DOOR IS OPEN - FALL BACK***",
    "en_trans": "",
    "zh_trans": "",
    "jp_trans": "",
    "kr_trans": "",
    "timer_num": 0,
    "enable_timer": 0
  },
  {
    "original": "***INCOMING TOAST - LEFT CHAMBER***",
    "en_trans": "",
    "zh_trans": "",
    "jp_trans": "",
    "kr_trans": "",
    "timer_num": 0,
    "enable_timer": 0
  },
  {
    "original": "***A TOASTER HAS BEEN PICKED UP***",
    "en_trans": "",
    "zh_trans": "",
    "jp_trans": "",
    "kr_trans": "",
    "timer_num": 0,
    "enable_timer": 0
  },
  {
    "original": "***THE PEANUT BUTTER HAS BEEN PICKED UP***",
    "en_trans": "",
    "zh_trans": "",
    "jp_trans": "",
    "kr_trans": "",
    "timer_num": 0,
    "enable_timer": 0
  },
  {
    "original": "***SOME SOUR MILK HAS BEEN PICKED UP***",
    "en_trans": "",
    "zh_trans": "",
    "jp_trans": "",
    "kr_trans": "",
    "timer_num": 0,
    "enable_timer": 0
  },
  {
    "original": "***YUUCK***",
    "en_trans": "",
    "zh_trans": "",
    "jp_trans": "",
    "kr_trans": "",
    "timer_num": 0,
    "enable_timer": 0
  },
  {
    "original": "***INCOMING TOAST - BOTH CHAMBERS***",
    "en_trans": "",
    "zh_trans": "",
    "jp_trans": "",
    "kr_trans": "",
    "timer_num": 0,
    "enable_timer": 0
  },
  {
    "original": "***A METAL ASS HAS BEEN PICKED UP***",
    "en_trans": "",
    "zh_trans": "",
    "jp_trans": "",
    "kr_trans": "",
    "timer_num": 0,
    "enable_timer": 0
  },
  {
    "original": "***INCOMING TOAST - RIGHT CHAMBER***",
    "en_trans": "",
    "zh_trans": "",
    "jp_trans": "",
    "kr_trans": "",
    "timer_num": 0,
    "enable_timer": 0
  },
  {
    "original": "***A JALAPENO HAS BEEN PICKED UP***",
    "en_trans": "",
    "zh_trans": "",
    "jp_trans": "",
    "kr_trans": "",
    "timer_num": 0,
    "enable_timer": 0
  },
  {
    "original": "***ELEVATOR IS LEAVING IN 25 SECONDS***",
    "en_trans": "",
    "zh_trans": "",
    "jp_trans": "",
    "kr_trans": "",
    "timer_num": 25,
    "enable_timer": 1
  },
  {
    "original": "已加载修复神器卡人stripper(by bxzl)",
    "en_trans": "",
    "zh_trans": "",
    "jp_trans": "",
    "kr_trans": "",
    "timer_num": 0,
    "enable_timer": 0
  },
  {
    "original": "***DOOR OPENING IN 5 SECONDS***",
    "en_trans": "",
    "zh_trans": "",
    "jp_trans": "",
    "kr_trans": "",
    "timer_num": 5,
    "enable_timer": 1
  },
  {
    "original": "***DOOR IS OPEN***",
    "en_trans": "",
    "zh_trans": "",
    "jp_trans": "",
    "kr_trans": "",
    "timer_num": 0,
    "enable_timer": 0
  },
  {
    "original": "***LOCATE AND PRESS ALL FIVE BUTTONS***",
    "en_trans": "",
    "zh_trans": "",
    "jp_trans": "",
    "kr_trans": "",
    "timer_num": 0,
    "enable_timer": 0
  },
  {
    "original": "***INITIATE THE TOASTER***",
    "en_trans": "",
    "zh_trans": "",
    "jp_trans": "",
    "kr_trans": "",
    "timer_num": 0,
    "enable_timer": 0
  },
  {
    "original": "***BUTTON PRESSED***",
    "en_trans": "",
    "zh_trans": "",
    "jp_trans": "",
    "kr_trans": "",
    "timer_num": 0,
    "enable_timer": 0
  },
  {
    "original": "***SOMETHING IS BLOCKING THE LEVER***",
    "en_trans": "",
    "zh_trans": "",
    "jp_trans": "",
    "kr_trans": "",
    "timer_num": 0,
    "enable_timer": 0
  },
  {
    "original": "***BREAK THE BLOCKING METAL PIECE UNDERNEATH***",
    "en_trans": "",
    "zh_trans": "",
    "jp_trans": "",
    "kr_trans": "",
    "timer_num": 0,
    "enable_timer": 0
  },
  {
    "original": "***YOU DID IT***",
    "en_trans": "",
    "zh_trans": "",
    "jp_trans": "",
    "kr_trans": "",
    "timer_num": 0,
    "enable_timer": 0
  },
  {
    "original": "***HOLD THEM OFF UNTIL THE LEVER IS ALL THE WAY DOWN***",
    "en_trans": "",
    "zh_trans": "",
    "jp_trans": "",
    "kr_trans": "",
    "timer_num": 0,
    "enable_timer": 0
  },
  {
    "original": "***THE TOASTER HAS BEEN TURNED ON***",
    "en_trans": "",
    "zh_trans": "",
    "jp_trans": "",
    "kr_trans": "",
    "timer_num": 0,
    "enable_timer": 0
  },
  {
    "original": "***ESCAPE THE TOASTER***",
    "en_trans": "",
    "zh_trans": "",
    "jp_trans": "",
    "kr_trans": "",
    "timer_num": 0,
    "enable_timer": 0
  },
  {
    "original": "***THE TOASTER IS GOING TO TOAST TOAST IN 3 MINUTES***",
    "en_trans": "",
    "zh_trans": "",
    "jp_trans": "",
    "kr_trans": "",
    "timer_num": 3,
    "enable_timer": 1
  },
  {
    "original": "***GET OUT OF THE TOASTER***",
    "en_trans": "",
    "zh_trans": "",
    "jp_trans": "",
    "kr_trans": "",
    "timer_num": 0,
    "enable_timer": 0
  },
  {
    "original": "***THIS PLACE IS FALLING APART***",
    "en_trans": "",
    "zh_trans": "",
    "jp_trans": "",
    "kr_trans": "",
    "timer_num": 0,
    "enable_timer": 0
  },
  {
    "original": "***YOU MUST HURRY***",
    "en_trans": "",
    "zh_trans": "",
    "jp_trans": "",
    "kr_trans": "",
    "timer_num": 0,
    "enable_timer": 0
  },
  {
    "original": "***THE TOASTER IS ABOUT TO TOAST TOAST!***",
    "en_trans": "",
    "zh_trans": "",
    "jp_trans": "",
    "kr_trans": "",
    "timer_num": 0,
    "enable_timer": 0
  },
  {
    "original": "***RUN FOR IT***",
    "en_trans": "",
    "zh_trans": "",
    "jp_trans": "",
    "kr_trans": "",
    "timer_num": 0,
    "enable_timer": 0
  },
  {
    "original": "***THE TOASTER IS GOING TO TOAST TOAST IN 2 MINUTES***",
    "en_trans": "",
    "zh_trans": "",
    "jp_trans": "",
    "kr_trans": "",
    "timer_num": 2,
    "enable_timer": 1
  },
  {
    "original": "***REMOVING DEBRIS - 5 SECONDS***",
    "en_trans": "",
    "zh_trans": "",
    "jp_trans": "",
    "kr_trans": "",
    "timer_num": 5,
    "enable_timer": 1
  },
  {
    "original": "***DEBRIS REMOVED - FALL BACK***",
    "en_trans": "",
    "zh_trans": "",
    "jp_trans": "",
    "kr_trans": "",
    "timer_num": 0,
    "enable_timer": 0
  },
  {
    "original": "***THE TOASTER IS GOING TO TOAST TOAST IN 1 MINUTE***",
    "en_trans": "",
    "zh_trans": "",
    "jp_trans": "",
    "kr_trans": "",
    "timer_num": 1,
    "enable_timer": 1
  },
  {
    "original": "***THE TOASTER IS GOING TO TOAST TOAST IN 30 SECONDS***",
    "en_trans": "",
    "zh_trans": "",
    "jp_trans": "",
    "kr_trans": "",
    "timer_num": 30,
    "enable_timer": 1
  },
  {
    "original": "***THE STAIRS ARE BROKEN***",
    "en_trans": "",
    "zh_trans": "",
    "jp_trans": "",
    "kr_trans": "",
    "timer_num": 0,
    "enable_timer": 0
  },
  {
    "original": "***GET UP ALL THE WAY TO THE MIDDLE SECTION ON TOP***",
    "en_trans": "",
    "zh_trans": "",
    "jp_trans": "",
    "kr_trans": "",
    "timer_num": 0,
    "enable_timer": 0
  },
  {
    "original": "***HOLD THERE FOR AS LONG AS POSSIBLE BEFORE JUMPING ON THE TOASTER***",
    "en_trans": "",
    "zh_trans": "",
    "jp_trans": "",
    "kr_trans": "",
    "timer_num": 0,
    "enable_timer": 0
  },
  {
    "original": "***FLY OUT WITH THE TOAST OR DIE***",
    "en_trans": "",
    "zh_trans": "",
    "jp_trans": "",
    "kr_trans": "",
    "timer_num": 0,
    "enable_timer": 0
  },
  {
    "original": "***THE TOASTER IS GOING TO TOAST TOAST IN 20 SECONDS***",
    "en_trans": "",
    "zh_trans": "",
    "jp_trans": "",
    "kr_trans": "",
    "timer_num": 20,
    "enable_timer": 1
  },
  {
    "original": "***THE TOASTER IS ABOUT TO TOAST TOAST IN 10 SECONDS***",
    "en_trans": "",
    "zh_trans": "",
    "jp_trans": "",
    "kr_trans": "",
    "timer_num": 10,
    "enable_timer": 1
  },
  {
    "original": "***GET OUT OF THERE***",
    "en_trans": "",
    "zh_trans": "",
    "jp_trans": "",
    "kr_trans": "",
    "timer_num": 0,
    "enable_timer": 0
  },
  {
    "original": "***THE TOASTER IS ABOUT TO TOAST TOAST IN 5 SECONDS***",
    "en_trans": "",
    "zh_trans": "",
    "jp_trans": "",
    "kr_trans": "",
    "timer_num": 5,
    "enable_timer": 1
  },
  {
    "original": "***THE TOASTER IS ABOUT TO TOAST TOAST IN 4 SECONDS***",
    "en_trans": "",
    "zh_trans": "",
    "jp_trans": "",
    "kr_trans": "",
    "timer_num": 4,
    "enable_timer": 1
  },
  {
    "original": "***THE TOASTER IS ABOUT TO TOAST TOAST IN 3 SECONDS***",
    "en_trans": "",
    "zh_trans": "",
    "jp_trans": "",
    "kr_trans": "",
    "timer_num": 3,
    "enable_timer": 1
  },
  {
    "original": "***THE TOASTER IS ABOUT TO TOAST TOAST IN 2 SECONDS***",
    "en_trans": "",
    "zh_trans": "",
    "jp_trans": "",
    "kr_trans": "",
    "timer_num": 2,
    "enable_timer": 1
  },
  {
    "original": "***THE TOASTER IS ABOUT TO TOAST TOAST IN 1 SECOND***",
    "en_trans": "",
    "zh_trans": "",
    "jp_trans": "",
    "kr_trans": "",
    "timer_num": 1,
    "enable_timer": 1
  },
  {
    "original": "***THE TOASTER IS TOASTING TOAST***",
    "en_trans": "",
    "zh_trans": "",
    "jp_trans": "",
    "kr_trans": "",
    "timer_num": 0,
    "enable_timer": 0
  },
  {
    "original": "***GET TOASTED!***",
    "en_trans": "",
    "zh_trans": "",
    "jp_trans": "",
    "kr_trans": "",
    "timer_num": 0,
    "enable_timer": 0
  },
  {
    "original": "***YOU MADE IT***",
    "en_trans": "",
    "zh_trans": "",
    "jp_trans": "",
    "kr_trans": "",
    "timer_num": 0,
    "enable_timer": 0
  },
  {
    "original": "***YOU COMPLETED THE MISSION - AND ESCAPED THE TOASTER***",
    "en_trans": "",
    "zh_trans": "",
    "jp_trans": "",
    "kr_trans": "",
    "timer_num": 0,
    "enable_timer": 0
  },
  {
    "original": "***WAIT A SECOND...***",
    "en_trans": "",
    "zh_trans": "",
    "jp_trans": "",
    "kr_trans": "",
    "timer_num": 0,
    "enable_timer": 0
  },
  {
    "original": "***ITS NICOLAS CAGE!***",
    "en_trans": "",
    "zh_trans": "",
    "jp_trans": "",
    "kr_trans": "",
    "timer_num": 0,
    "enable_timer": 0
  },
  {
    "original": "***UR***",
    "en_trans": "",
    "zh_trans": "",
    "jp_trans": "",
    "kr_trans": "",
    "timer_num": 0,
    "enable_timer": 0
  },
  {
    "original": "***ELEVATOR IS LEAVING IN 10 SECONDS***",
    "en_trans": "",
    "zh_trans": "",
    "jp_trans": "",
    "kr_trans": "",
    "timer_num": 10,
    "enable_timer": 1
  },
  {
    "original": "***ELEVATOR IS LEAVING IN 5 SECONDS***",
    "en_trans": "",
    "zh_trans": "",
    "jp_trans": "",
    "kr_trans": "",
    "timer_num": 5,
    "enable_timer": 1
  },
  {
    "original": "***ELEVATOR IS LEAVING IN 4 SECONDS***",
    "en_trans": "",
    "zh_trans": "",
    "jp_trans": "",
    "kr_trans": "",
    "timer_num": 4,
    "enable_timer": 1
  },
  {
    "original": "***ELEVATOR IS LEAVING IN 3 SECONDS***",
    "en_trans": "",
    "zh_trans": "",
    "jp_trans": "",
    "kr_trans": "",
    "timer_num": 3,
    "enable_timer": 1
  },
  {
    "original": "***ELEVATOR IS LEAVING IN 2 SECONDS***",
    "en_trans": "",
    "zh_trans": "",
    "jp_trans": "",
    "kr_trans": "",
    "timer_num": 2,
    "enable_timer": 1
  },
  {
    "original": "***LAGEVATOR IS LEAVING IN 1 SECOND***",
    "en_trans": "",
    "zh_trans": "",
    "jp_trans": "",
    "kr_trans": "",
    "timer_num": 1,
    "enable_timer": 1
  },
  {
    "original": "***ELEVATOR IS LEAVING***",
    "en_trans": "",
    "zh_trans": "",
    "jp_trans": "",
    "kr_trans": "",
    "timer_num": 0,
    "enable_timer": 0
  },
  {
    "original": "***DOOR OPENING IN 20 SECONDS***",
    "en_trans": "",
    "zh_trans": "",
    "jp_trans": "",
    "kr_trans": "",
    "timer_num": 20,
    "enable_timer": 1
  },
  {
    "original": "已加载修复神器卡人new stripper(by bxzl)",
    "en_trans": "",
    "zh_trans": "",
    "jp_trans": "",
    "kr_trans": "",
    "timer_num": 0,
    "enable_timer": 0
  }
]