[
  {
    "original": "!!! BOX SPAWNER !!!",
    "en_trans": "",
    "zh_trans": "!!! 箱子搬运工 !!!",
    "jp_trans": "",
    "kr_trans": "",
    "timer_num": 0,
    "enable_timer": 0
  },
  {
    "original": "<< DEFEND HERE >>",
    "en_trans": "",
    "zh_trans": "<< 守住这里 >>",
    "jp_trans": "",
    "kr_trans": "",
    "timer_num": 0,
    "enable_timer": 0
  },
  {
    "original": "<<< FALL BACK >>>",
    "en_trans": "",
    "zh_trans": "<< 撤退 >>",
    "jp_trans": "",
    "kr_trans": "",
    "timer_num": 0,
    "enable_timer": 0
  },
  {
    "original": "<< LEVEL 1 >>",
    "en_trans": "",
    "zh_trans": "<< 关卡 1 >>",
    "jp_trans": "",
    "kr_trans": "",
    "timer_num": 1,
    "enable_timer": 1
  },
  {
    "original": "<< CHECKPOINTS >>",
    "en_trans": "",
    "zh_trans": "<< 存点 >>",
    "jp_trans": "",
    "kr_trans": "",
    "timer_num": 0,
    "enable_timer": 0
  },
  {
    "original": "<< CHECKPOINT 1 >>",
    "en_trans": "",
    "zh_trans": "<< 存点 1 >>",
    "jp_trans": "",
    "kr_trans": "",
    "timer_num": 0,
    "enable_timer": 0
  },
  {
    "original": "<< DOOR OPEN 25 SECONDS >>",
    "en_trans": "",
    "zh_trans": "<< 25秒开门 >>",
    "jp_trans": "",
    "kr_trans": "",
    "timer_num": 25,
    "enable_timer": 1
  },
  {
    "original": "<< DOOR OPEN >>",
    "en_trans": "",
    "zh_trans": "<< 开门 >>",
    "jp_trans": "",
    "kr_trans": "",
    "timer_num": 0,
    "enable_timer": 0
  },
  {
    "original": "<< DOOR CLOSING >>",
    "en_trans": "",
    "zh_trans": "<< 关门 >>",
    "jp_trans": "",
    "kr_trans": "",
    "timer_num": 0,
    "enable_timer": 0
  },
  {
    "original": "<< PRESS AND HOLD >>",
    "en_trans": "",
    "zh_trans": "<< 长按按钮 >>",
    "jp_trans": "",
    "kr_trans": "",
    "timer_num": 0,
    "enable_timer": 0
  },
  {
    "original": "<<< CAUTION : FAN AUTOMATIC START >>>",
    "en_trans": "",
    "zh_trans": "<< 警告：风扇启动 >>",
    "jp_trans": "",
    "kr_trans": "",
    "timer_num": 0,
    "enable_timer": 0
  },
  {
    "original": "<< DOOR OPEN 15 SECONDS >>",
    "en_trans": "",
    "zh_trans": "<< 15秒开门 >>",
    "jp_trans": "",
    "kr_trans": "",
    "timer_num": 15,
    "enable_timer": 1
  },
  {
    "original": "<< CHECKPOINT 2 >>",
    "en_trans": "",
    "zh_trans": "<< 存点 2 >>",
    "jp_trans": "",
    "kr_trans": "",
    "timer_num": 0,
    "enable_timer": 0
  },
  {
    "original": "<< DOOR OPEN 20 SECONDS >>",
    "en_trans": "",
    "zh_trans": "<< 20秒开门 >>",
    "jp_trans": "",
    "kr_trans": "",
    "timer_num": 20,
    "enable_timer": 1
  },
  {
    "original": "<< DOOR CLOSING 5 SECONDS >>",
    "en_trans": "",
    "zh_trans": "<< 5秒后关门 >>",
    "jp_trans": "",
    "kr_trans": "",
    "timer_num": 5,
    "enable_timer": 1
  },
  {
    "original": "<< FALL BACK >>",
    "en_trans": "",
    "zh_trans": "<< 撤退 >>",
    "jp_trans": "",
    "kr_trans": "",
    "timer_num": 0,
    "enable_timer": 0
  },
  {
    "original": "<< CHECKPOINT 3 >>",
    "en_trans": "",
    "zh_trans": "<< 存点 3 >>",
    "jp_trans": "",
    "kr_trans": "",
    "timer_num": 0,
    "enable_timer": 0
  },
  {
    "original": "< BREAK TRAM >",
    "en_trans": "",
    "zh_trans": "< 破坏缆车 >",
    "jp_trans": "",
    "kr_trans": "",
    "timer_num": 0,
    "enable_timer": 0
  },
  {
    "original": "< DROP CRATE INTO HOLE >",
    "en_trans": "",
    "zh_trans": "< 把箱子打下子接住 >",
    "jp_trans": "",
    "kr_trans": "",
    "timer_num": 0,
    "enable_timer": 0
  },
  {
    "original": "< TO SPAWN CRATE >",
    "en_trans": "",
    "zh_trans": "< 去获得箱子 >",
    "jp_trans": "",
    "kr_trans": "",
    "timer_num": 0,
    "enable_timer": 0
  },
  {
    "original": "<< BOX SPAWNED >>",
    "en_trans": "",
    "zh_trans": "<< 箱子已生成 >>",
    "jp_trans": "",
    "kr_trans": "",
    "timer_num": 0,
    "enable_timer": 0
  },
  {
    "original": "<< CHECKPOINT 4 >>",
    "en_trans": "",
    "zh_trans": "<< 存点 4 >>",
    "jp_trans": "",
    "kr_trans": "",
    "timer_num": 0,
    "enable_timer": 0
  },
  {
    "original": "<< DOOR OPENING 10 SECONDS >>",
    "en_trans": "",
    "zh_trans": "<< 10秒开门 >>",
    "jp_trans": "",
    "kr_trans": "",
    "timer_num": 10,
    "enable_timer": 1
  },
  {
    "original": "< FAN ACTIVATING >",
    "en_trans": "",
    "zh_trans": "< 风扇启动 >",
    "jp_trans": "",
    "kr_trans": "",
    "timer_num": 0,
    "enable_timer": 0
  },
  {
    "original": "< USE BLOCKS FOR COVER >",
    "en_trans": "",
    "zh_trans": "< 用箱子来做掩体 >",
    "jp_trans": "",
    "kr_trans": "",
    "timer_num": 0,
    "enable_timer": 0
  },
  {
    "original": "<< FINAL DOOR CLOSING 20 SECONDS >>",
    "en_trans": "",
    "zh_trans": "<< 最后的门20秒关闭 >>",
    "jp_trans": "",
    "kr_trans": "",
    "timer_num": 20,
    "enable_timer": 1
  },
  {
    "original": "<< LEVEL 1 - CHECKPOINTS WON >>",
    "en_trans": "",
    "zh_trans": "<< 关卡1 - 存点模式 胜利！ >>",
    "jp_trans": "",
    "kr_trans": "",
    "timer_num": 0,
    "enable_timer": 0
  },
  {
    "original": "<< LEVEL 2 >>",
    "en_trans": "",
    "zh_trans": "<< 关卡2 >>",
    "jp_trans": "",
    "kr_trans": "",
    "timer_num": 0,
    "enable_timer": 0
  },
  {
    "original": "<<< CHECKPOINT 1 >>>",
    "en_trans": "",
    "zh_trans": "<< 存点1 >>",
    "jp_trans": "",
    "kr_trans": "",
    "timer_num": 0,
    "enable_timer": 0
  },
  {
    "original": "<< DOOR OPENING 8 SECONDS >>",
    "en_trans": "",
    "zh_trans": "<< 8秒开门 >>",
    "jp_trans": "",
    "kr_trans": "",
    "timer_num": 8,
    "enable_timer": 1
  },
  {
    "original": "<<< DEFEND HERE >>>",
    "en_trans": "",
    "zh_trans": "<<< 守住这里 >>>",
    "jp_trans": "",
    "kr_trans": "",
    "timer_num": 0,
    "enable_timer": 0
  },
  {
    "original": "<< DOOR OPENING 15 SECONDS >>",
    "en_trans": "",
    "zh_trans": "<< 15秒开门 >>",
    "jp_trans": "",
    "kr_trans": "",
    "timer_num": 15,
    "enable_timer": 1
  },
  {
    "original": "<<< CHECKPOINT 2 >>>",
    "en_trans": "",
    "zh_trans": "<<< 存点2 >>>",
    "jp_trans": "",
    "kr_trans": "",
    "timer_num": 0,
    "enable_timer": 0
  },
  {
    "original": "< PUSH CART >",
    "en_trans": "",
    "zh_trans": "< 推车 >",
    "jp_trans": "",
    "kr_trans": "",
    "timer_num": 0,
    "enable_timer": 0
  },
  {
    "original": "< 6 PLAYERS - MAX SPEED >",
    "en_trans": "",
    "zh_trans": "< 6个玩家推车 - 速度就可以达到最快 >",
    "jp_trans": "",
    "kr_trans": "",
    "timer_num": 0,
    "enable_timer": 0
  },
  {
    "original": "< HUMANS - PROTECT THE CART >",
    "en_trans": "",
    "zh_trans": "< 人类任务 - 保护好这个手推车 >",
    "jp_trans": "",
    "kr_trans": "",
    "timer_num": 0,
    "enable_timer": 0
  },
  {
    "original": "< ZOMBIES - DESTROY THE CART >",
    "en_trans": "",
    "zh_trans": "< 僵尸任务 - 摧毁手推车 >",
    "jp_trans": "",
    "kr_trans": "",
    "timer_num": 0,
    "enable_timer": 0
  },
  {
    "original": "<< CART HEALTH - 75% >>",
    "en_trans": "",
    "zh_trans": "<< 手推车血量 - 75% >>",
    "jp_trans": "",
    "kr_trans": "",
    "timer_num": 0,
    "enable_timer": 0
  },
  {
    "original": "<< CART HEALTH - 50% >>",
    "en_trans": "",
    "zh_trans": "<< 手推车血量 - 50% >>",
    "jp_trans": "",
    "kr_trans": "",
    "timer_num": 0,
    "enable_timer": 0
  },
  {
    "original": "<<< CHECKPOINT 3 >>>",
    "en_trans": "",
    "zh_trans": "<<< 存点 3 >>>",
    "jp_trans": "",
    "kr_trans": "",
    "timer_num": 0,
    "enable_timer": 0
  },
  {
    "original": "<< CART HEALTH - 25% >>",
    "en_trans": "",
    "zh_trans": "<< 手推车血量 - 25% >>",
    "jp_trans": "",
    "kr_trans": "",
    "timer_num": 0,
    "enable_timer": 0
  },
  {
    "original": "<< CART HEALTH - 10% >>",
    "en_trans": "",
    "zh_trans": "<< 手推车血量 - 10% >>",
    "jp_trans": "",
    "kr_trans": "",
    "timer_num": 0,
    "enable_timer": 0
  },
  {
    "original": "<< CART DESTROYED >>",
    "en_trans": "",
    "zh_trans": "<< 手推车被摧毁 完辣！ >>",
    "jp_trans": "",
    "kr_trans": "",
    "timer_num": 0,
    "enable_timer": 0
  },
  {
    "original": "<< LIFT LEAVING 15 SECONDS >>",
    "en_trans": "",
    "zh_trans": "<< 电梯15秒后离开 >>",
    "jp_trans": "",
    "kr_trans": "",
    "timer_num": 15,
    "enable_timer": 1
  },
  {
    "original": "<< LIFT LEAVING >>",
    "en_trans": "",
    "zh_trans": "<< 电梯离开 >>",
    "jp_trans": "",
    "kr_trans": "",
    "timer_num": 0,
    "enable_timer": 0
  },
  {
    "original": "<<< CHECKPOINT 4 >>>",
    "en_trans": "",
    "zh_trans": "<<< 存点 4 >>>",
    "jp_trans": "",
    "kr_trans": "",
    "timer_num": 0,
    "enable_timer": 0
  },
  {
    "original": "< THROW NADE IN HOLE >",
    "en_trans": "",
    "zh_trans": "< 把手雷丢进这个洞里获取箱子 >",
    "jp_trans": "",
    "kr_trans": "",
    "timer_num": 0,
    "enable_timer": 0
  },
  {
    "original": "<< DOOR OPEN 10 SECONDS >>",
    "en_trans": "",
    "zh_trans": "<< 10秒开门 >>",
    "jp_trans": "",
    "kr_trans": "",
    "timer_num": 10,
    "enable_timer": 1
  },
  {
    "original": "<<< DOOR OPEN >>>",
    "en_trans": "",
    "zh_trans": "<< 开门 >>",
    "jp_trans": "",
    "kr_trans": "",
    "timer_num": 0,
    "enable_timer": 0
  },
  {
    "original": "<< RIGHT BRIDGE ACTIVE >>",
    "en_trans": "",
    "zh_trans": "<< 右边的桥已被机会 >>",
    "jp_trans": "",
    "kr_trans": "",
    "timer_num": 0,
    "enable_timer": 0
  },
  {
    "original": "<< DOOR OPENING 20 SECONDS >>",
    "en_trans": "",
    "zh_trans": "<< 20秒后开门 >>",
    "jp_trans": "",
    "kr_trans": "",
    "timer_num": 20,
    "enable_timer": 1
  },
  {
    "original": "<<< CHECKPOINT 5 >>>",
    "en_trans": "",
    "zh_trans": "<<< 存点 5 >>>",
    "jp_trans": "",
    "kr_trans": "",
    "timer_num": 0,
    "enable_timer": 0
  },
  {
    "original": "<< KEEP ZOMBIES OFF TRAM >>",
    "en_trans": "",
    "zh_trans": "<< 守住 别让僵尸上缆车 >>",
    "jp_trans": "",
    "kr_trans": "",
    "timer_num": 0,
    "enable_timer": 0
  },
  {
    "original": "<<< LAST DOOR OPEN >>>",
    "en_trans": "",
    "zh_trans": "<<< 最后的门开启 >>>",
    "jp_trans": "",
    "kr_trans": "",
    "timer_num": 0,
    "enable_timer": 0
  },
  {
    "original": "<<< BUILD TOWER TO PLATFORM >>>",
    "en_trans": "",
    "zh_trans": "<<< 我们得用箱子搭上去这个平台（或者用些箱子做别的事情？） >>>",
    "jp_trans": "",
    "kr_trans": "",
    "timer_num": 0,
    "enable_timer": 0
  },
  {
    "original": "<< MAP COMPLETE - CHECKPOINTS >>",
    "en_trans": "",
    "zh_trans": "<< 地图全通关 - 存点模式 >>",
    "jp_trans": "",
    "kr_trans": "",
    "timer_num": 0,
    "enable_timer": 0
  },
  {
    "original": "<< NO CHECKPOINTS >>",
    "en_trans": "",
    "zh_trans": "<< 无存点模式 >>",
    "jp_trans": "",
    "kr_trans": "",
    "timer_num": 0,
    "enable_timer": 0
  },
  {
    "original": "<<< ZOMBIE DETECTED >>>",
    "en_trans": "",
    "zh_trans": "<<< 检测到僵尸 >>>",
    "jp_trans": "",
    "kr_trans": "",
    "timer_num": 0,
    "enable_timer": 0
  },
  {
    "original": "< CATCH CRATE >",
    "en_trans": "",
    "zh_trans": "< 追上箱子 >",
    "jp_trans": "",
    "kr_trans": "",
    "timer_num": 0,
    "enable_timer": 0
  },
  {
    "original": "<< LEFT BRIDGE ACTIVE >>",
    "en_trans": "",
    "zh_trans": "<< 左边桥梁激活 >>",
    "jp_trans": "",
    "kr_trans": "",
    "timer_num": 0,
    "enable_timer": 0
  },
  {
    "original": "<< STEPS OPEN >>",
    "en_trans": "",
    "zh_trans": "",
    "jp_trans": "",
    "kr_trans": "",
    "timer_num": 0,
    "enable_timer": 0
  },
  {
    "original": "< CATCH BOX >",
    "en_trans": "",
    "zh_trans": "",
    "jp_trans": "",
    "kr_trans": "",
    "timer_num": 0,
    "enable_timer": 0
  },
  {
    "original": "<< DOOR OPEN 30 SECONDS >>",
    "en_trans": "",
    "zh_trans": "",
    "jp_trans": "",
    "kr_trans": "",
    "timer_num": 30,
    "enable_timer": 1
  },
  {
    "original": "<< FINAL DOOR CLOSING 30 SECONDS >>",
    "en_trans": "",
    "zh_trans": "",
    "jp_trans": "",
    "kr_trans": "",
    "timer_num": 30,
    "enable_timer": 1
  },
  {
    "original": "<< DOOR OPENING >>",
    "en_trans": "",
    "zh_trans": "",
    "jp_trans": "",
    "kr_trans": "",
    "timer_num": 0,
    "enable_timer": 0
  }
]